clientforge/__init__.py
clientforge/exceptions.py
clientforge/auth/__init__.py
clientforge/auth/base.py
clientforge/auth/oauth2.py
clientforge/clients/__init__.py
clientforge/clients/async_.py
clientforge/clients/base.py
clientforge/clients/sync.py
clientforge/models/__init__.py
clientforge/models/fields.py
clientforge/models/results.py
clientforge/paginate/__init__.py
clientforge/paginate/base.py
clientforge/paginate/offset.py
clientforge-0.6.0.dist-info/METADATA
clientforge-0.6.0.dist-info/WHEEL
clientforge-0.6.0.dist-info/licenses/LICENSE
clientforge-0.6.0.dist-info/RECORD
